bowlstoy/BowlConsole.py
bowlstoy/BowlFTP.py
bowlstoy/BowlFile.py
bowlstoy/BowlLog.py
bowlstoy/BowlSMB.py
bowlstoy/BowlSSH.py
bowlstoy/BowlSVN.py
bowlstoy/BowlTime.py
bowlstoy/BowlUnity.py
bowlstoy/BowlXCode.py
bowlstoy/__init__.py
bowlstoy-0.0.3.dist-info/LICENSE.txt
bowlstoy-0.0.3.dist-info/METADATA
bowlstoy-0.0.3.dist-info/WHEEL
bowlstoy-0.0.3.dist-info/top_level.txt
bowlstoy-0.0.3.dist-info/RECORD
