Metadata-Version: 2.1
Name: bowlstoy
Version: 0.0.3
Summary: simple python tool
Home-page: 
Author: Bowl
Author-email: wangdi640@gmail.com
Classifier: Programming Language :: Python :: 3
Classifier: License :: OSI Approved :: MIT License
Classifier: Operating System :: OS Independent
Requires-Python: >=3.7
License-File: LICENSE.txt
Requires-Dist: scp (>=0.14.4)
Requires-Dist: paramiko (>=2.10.3)
Requires-Dist: pyftpdlib (>=1.5.6)
Requires-Dist: pysmb (>=1.2.9.1)
